client/__init__.py
client/client_run.py
client/client/__init__.py
client/client/add_contact.py
client/client/database.py
client/client/del_contact.py
client/client/main_window.py
client/client/main_window_conv.py
client/client/start_dialog.py
client/client/transport.py
client/common/__init__.py
client/common/decorate.py
client/common/descryptors.py
client/common/errors.py
client/common/metaclasses.py
client/common/utils.py
client/common/variables.py
client/proj_log/__init__.py
client/unit_tests/__init__.py
py_CS_august_client-0.0.1.dist-info/METADATA
py_CS_august_client-0.0.1.dist-info/WHEEL
py_CS_august_client-0.0.1.dist-info/top_level.txt
py_CS_august_client-0.0.1.dist-info/RECORD
